LICENSE
README.md
setup.py
myca/__init__.py
myca.egg-info/PKG-INFO
myca.egg-info/SOURCES.txt
myca.egg-info/dependency_links.txt
myca.egg-info/requires.txt
myca.egg-info/top_level.txt
myca/architecture/__init__.py
myca/architecture/tars.py
myca/dataset/__init__.py
myca/dataset/aggregate.py
myca/dataset/clean.py
myca/dataset/raw.py
myca/dataset/util.py
myca/util/__init__.py
myca/util/_data_path.py
myca/util/util.py